marksman/__init__.py
marksman/app.py
marksman/cli.py
marksman/db.py
marksman/helpers.py
marksman/mailer.py
marksman/models.py
marksman/plot.py
marksman/settings.py
marksman/utils.py
marksman/validators.py
marksman-0.6.7.dist-info/LICENSE
marksman-0.6.7.dist-info/METADATA
marksman-0.6.7.dist-info/WHEEL
marksman-0.6.7.dist-info/entry_points.txt
marksman-0.6.7.dist-info/top_level.txt
marksman-0.6.7.dist-info/RECORD
