Metadata-Version: 2.1
Name: marksman
Version: 0.6.7
Summary: CLI Tool to manage marks of students efficiently.
Home-page: https://github.com/aahnik/cbse-xii-cs-proj/tree/main/project
Author: Aahnik Daw
Author-email: meet.aahnik@gmail.com
License: MIT License
Keywords: sql,database,crud,marks management,cms,data management,cli,utility,tool
Platform: UNKNOWN
Classifier: Programming Language :: Python :: 3
Classifier: License :: OSI Approved :: MIT License
Classifier: Operating System :: OS Independent
Requires-Python: >=3.8
Requires-Dist: matplotlib
Requires-Dist: PyQt5
Requires-Dist: Markdown
Requires-Dist: rich
Requires-Dist: python-dotenv
